src/main.py
pdfcrop_cli-0.3.0.dist-info/METADATA
pdfcrop_cli-0.3.0.dist-info/WHEEL
pdfcrop_cli-0.3.0.dist-info/entry_points.txt
pdfcrop_cli-0.3.0.dist-info/licenses/LICENSE
pdfcrop_cli-0.3.0.dist-info/RECORD
