Metadata-Version: 2.4
Name: pdfcrop-cli
Version: 0.3.0
Summary: An experimental alternative of TeX/pdfcrop tool
Author-email: Jiadong He <jiadonghe007@gmail.com>
License-Expression: AGPL-3.0
License-File: LICENSE
Classifier: Operating System :: OS Independent
Classifier: Programming Language :: Python :: 3
Requires-Python: >=3.10
Requires-Dist: pymupdf>=1.25.2
Requires-Dist: tyro>=0.9.13
